README.rst
setup.py
bitpay/__init__.py
bitpay/api.py
python_bitpay.egg-info/PKG-INFO
python_bitpay.egg-info/SOURCES.txt
python_bitpay.egg-info/dependency_links.txt
python_bitpay.egg-info/not-zip-safe
python_bitpay.egg-info/top_level.txt