Metadata-Version: 1.0
Name: python-bitpay
Version: 0.0.1
Summary: BitPay API wrapper for Python
Home-page: https://github.com/JonnyFunFun/python-bitpay
Author: Jonathan Enzinna
Author-email: jonnyfunfun@gmail.com
License: GPLv3
Keywords: bitcoin,btc,bitpay
Platform: UNKNOWN
Classifier: Development Status :: 4 - Beta
Classifier: Intended Audience :: Developers
Classifier: License :: OSI Approved :: GNU General Public License (GPL)
Classifier: Natural Language :: English
Classifier: Operating System :: OS Independent
Classifier: Programming Language :: Python :: 2.6
Classifier: Programming Language :: Python :: 2.7
Classifier: Topic :: Office/Business :: Financial
Classifier: Topic :: Software Development :: Libraries
Classifier: Topic :: Utilities
